SparkToPandas/__init__.py
SparkToPandas/pandas_plugin.py
sparktopandas-1.0.4.dist-info/METADATA
sparktopandas-1.0.4.dist-info/WHEEL
sparktopandas-1.0.4.dist-info/licenses/LICENSE
sparktopandas-1.0.4.dist-info/RECORD
