Metadata-Version: 2.1
Name: SparkToPandas
Version: 1.0.4
Summary: A pyspark package with the syntax similar to pandas.
Project-URL: Homepage, https://github.com/govardhan26/SparkToPandas
Project-URL: Bug Tracker, https://github.com/govardhan26/SparkToPandas/issues
Project-URL: Donate, https://www.buymeacoffee.com/govardhan26
Project-URL: linkedin, https://www.linkedin.com/in/govardhan-selvaraj/
Project-URL: Docs, https://sparktopandas.readthedocs.io/en/latest/index.html
Author-email: Govardhan Selvaraj <govardhan_selvaraj@yahoo.com>
License-File: LICENSE
Classifier: License :: OSI Approved :: MIT License
Classifier: Operating System :: OS Independent
Classifier: Programming Language :: Python :: 3
Requires-Python: >=3.8
